ivolatility/__init__.py
ivolatility/ivolatility.py
ivolatility-1.9.0.dist-info/LICENSE
ivolatility-1.9.0.dist-info/METADATA
ivolatility-1.9.0.dist-info/WHEEL
ivolatility-1.9.0.dist-info/top_level.txt
ivolatility-1.9.0.dist-info/RECORD
