Metadata-Version: 2.1
Name: ivolatility
Version: 1.9.0
Summary: IVolatility API wrapper package
Home-page: https://redocly.github.io/redoc/?nocors&url=https://restapi.ivolatility.com/api-docs
Author: IVolatility
Author-email: support@ivolatility.com
License: BSD 2-clause
Classifier: Development Status :: 5 - Production/Stable
Classifier: Intended Audience :: End Users/Desktop
Classifier: License :: OSI Approved :: BSD License
Classifier: Programming Language :: Python :: 3
Classifier: Programming Language :: Python :: 3.7
Classifier: Programming Language :: Python :: 3.8
Classifier: Programming Language :: Python :: 3.9
Classifier: Programming Language :: Python :: 3.10
Classifier: Programming Language :: Python :: 3.11
License-File: LICENSE
Requires-Dist: pandas
Requires-Dist: requests
